riggery/__init__.py
riggery/core/__init__.py
riggery/core/cmds.py
riggery/core/elem.py
riggery/core/wrap.py
riggery/core/datatypes/__init__.py
riggery/core/datatypes/boundingBox.py
riggery/core/datatypes/data.py
riggery/core/datatypes/eulerRotation.py
riggery/core/datatypes/matrix.py
riggery/core/datatypes/point.py
riggery/core/datatypes/quaternion.py
riggery/core/datatypes/tensor.py
riggery/core/datatypes/tensor2.py
riggery/core/datatypes/tensor3.py
riggery/core/datatypes/tensor4.py
riggery/core/datatypes/vector.py
riggery/core/lib/__init__.py
riggery/core/lib/controls.py
riggery/core/lib/controlshapes.json
riggery/core/lib/controlshapes.py
riggery/core/lib/evaluation.py
riggery/core/lib/geo.py
riggery/core/lib/grouptree.py
riggery/core/lib/mathops.py
riggery/core/lib/mixedmode.py
riggery/core/lib/names.py
riggery/core/lib/namespaces.py
riggery/core/lib/nativeunits.py
riggery/core/lib/nodetracker.py
riggery/core/lib/ntsuffixes.json
riggery/core/lib/nurbsutil.py
riggery/core/lib/skel.py
riggery/core/lib/tags.py
riggery/core/lib/triadutil.py
riggery/core/lib/undo.py
riggery/core/nodetypes/__init__.py
riggery/core/nodetypes/bezierCurve.py
riggery/core/nodetypes/cluster.py
riggery/core/nodetypes/dagNode.py
riggery/core/nodetypes/deformableShape.py
riggery/core/nodetypes/dependNode.py
riggery/core/nodetypes/fourByFourMatrix.py
riggery/core/nodetypes/geometryFilter.py
riggery/core/nodetypes/geometryShape.py
riggery/core/nodetypes/ikHandle.py
riggery/core/nodetypes/joint.py
riggery/core/nodetypes/network.py
riggery/core/nodetypes/nurbsCurve.py
riggery/core/nodetypes/objectSet.py
riggery/core/nodetypes/remapValue.py
riggery/core/nodetypes/shape.py
riggery/core/nodetypes/skinCluster.py
riggery/core/nodetypes/subdiv.py
riggery/core/nodetypes/surfaceShape.py
riggery/core/nodetypes/transform.py
riggery/core/plugtypes/__init__.py
riggery/core/plugtypes/angle.py
riggery/core/plugtypes/attribute.py
riggery/core/plugtypes/bezierCurve.py
riggery/core/plugtypes/bool.py
riggery-0.1.dist-info/licenses/LICENSE
riggery-0.1.dist-info/METADATA
riggery-0.1.dist-info/WHEEL
riggery-0.1.dist-info/top_level.txt
riggery-0.1.dist-info/RECORD
