Metadata-Version: 2.4
Name: riggery
Version: 0.1
Summary: An object-oriented, operator-overloaded rigging library for Maya.
Author-email: Kimon Matara <kimon@riggery.com>
License-Expression: MIT
Classifier: Programming Language :: Python :: 3
Classifier: Operating System :: OS Independent
Classifier: Development Status :: 4 - Beta
Classifier: Topic :: Artistic Software
Classifier: Topic :: Software Development :: Libraries :: Python Modules
Requires-Python: >=3.8
License-File: LICENSE
Dynamic: license-file
